{
    "buildings": [
        {
            "levels": 3,
            "polygon": [
                {
                    "x": 40.0,
                    "y": 50.0
                },
                {
                    "x": 40.0,
                    "y": 55.0
                },
                {
                    "x": 45.0,
                    "y": 55.0
                },
                {
                    "x": 45.0,
                    "y": 50.0
                }
            ]
        }
    ],
    "highways": [
        {
            "polygon": [
                {
                    "x": 40.0,
                    "y": 50.0
                },
                {
                    "x": 40.0,
                    "y": 55.0
                },
                {
                    "x": 45.0,
                    "y": 55.0
                },
                {
                    "x": 45.0,
                    "y": 50.0
                }
            ]
        }
    ]
}